Metadata-Version: 1.0
Name: socketsws
Version: 1.0.0
Summary: Stream HTML To Local Server
Home-page: UNKNOWN
Author: UNKNOWN
Author-email: UNKNOWN
License: UNKNOWN
Platform: UNKNOWN
